RAM/source_RAM.v
module source(clk,data,addr,we);
	input clk;
	output reg [7:0] data;
	output reg [5:0] addr;
	output reg we;	
	
	initial
	begin
		we = 1;
		data = 0;
		addr = 0;
		
	end
	
	always @ (posedge clk)
	begin
		addr = data + 5;
		data = data + 5;  
		//#2;
		//addr = 20;
		//data = 20;
		//#2;
		//addr = 30;
		//data = 30;
		
	end
endmodule

RAM/RAM.v
module RAM (
	input [7:0] data,
	input [5:0] addr,
	input we, clk,
	output [5:0] q
);

	// declara a variável RAM
	reg [7:0] ram[63:0];

	// variável para guardar o endereco de dado registrado
	reg [5:0] addr_reg;

	always @ (posedge clk)
	begin
		// Escreve
		if (we)  // Write enable  
			ram[addr] <= data;
		addr_reg <= addr;
	end

	// Continuous assignment implies read returns NEW data.	
	assign q = ram[addr_reg];

endmodule

RAM/RAM_tb.v
`include "RAM.v"
`include "source_RAM.v"

module machine_tb;
	wire [7:0] data;
	wire [5:0] addr; 
	wire we;
	wire [5:0] q;
	reg clock;
	
	RAM RAM(
		.data(data),
		.addr(addr),
		.we(we),
		.clk(clock),
		.q(q)
	);

	source source(
		.we(we),
		.addr(addr),
		.data(data),		
		.clk(clock)	
	);

	initial // Tudo dentro é executado somente uma vez
	begin
		$dumpfile("wave.vcd"); // Especifica o arquivo 
		$dumpvars; // Especifica pra colocar todos os sinais 
		clock = 0;
		#1000 $finish;
	end
	always
	#3 clock = ~clock;
endmodule

RAM/wave.vcd
$date
	Wed Apr 18 10:34:15 2018
$end
$version
	Icarus Verilog
$end
$timescale
	1s
$end
$scope module machine_tb $end
$var wire 6 ! addr [5:0] $end
$var wire 8 " data [7:0] $end
$var wire 6 # q [5:0] $end
$var wire 1 $ we $end
$var reg 1 % clock $end
$scope module RAM $end
$var wire 6 & addr [5:0] $end
$var wire 1 ' clk $end
$var wire 8 ( data [7:0] $end
$var wire 6 ) q [5:0] $end
$var wire 1 $ we $end
$var reg 6 * addr_reg [5:0] $end
$upscope $end
$scope module source $end
$var wire 1 ' clk $end
$var reg 6 + addr [5:0] $end
$var reg 8 , data [7:0] $end
$var reg 1 - we $end
$upscope $end
$upscope $end
$enddefinitions $end
#0
$dumpvars
1-
b0 ,
b0 +
bx *
bx )
b0 (
0'
b0 &
0%
1$
bx #
b0 "
b0 !
$end
#3
b101 #
b101 )
b101 *
b101 ,
b101 "
b101 (
b101 +
b101 !
b101 &
1%
1'
#6
0%
0'
#9
b1010 ,
b1010 "
b1010 (
b1010 +
b1010 !
b1010 &
1%
1'
#12
0%
0'
#15
b1111 #
b1111 )
b1111 *
b1111 ,
b1111 "
b1111 (
b1111 +
b1111 !
b1111 &
1%
1'
#18
0%
0'
#21
b10100 ,
b10100 "
b10100 (
b10100 +
b10100 !
b10100 &
1%
1'
#24
0%
0'
#27
b11001 #
b11001 )
b11001 *
b11001 ,
b11001 "
b11001 (
b11001 +
b11001 !
b11001 &
1%
1'
#30
0%
0'
#33
b11110 ,
b11110 "
b11110 (
b11110 +
b11110 !
b11110 &
1%
1'
#36
0%
0'
#39
b100011 #
b100011 )
b100011 *
b100011 ,
b100011 "
b100011 (
b100011 +
b100011 !
b100011 &
1%
1'
#42
0%
0'
#45
b101000 ,
b101000 "
b101000 (
b101000 +
b101000 !
b101000 &
1%
1'
#48
0%
0'
#51
b101101 #
b101101 )
b101101 *
b101101 ,
b101101 "
b101101 (
b101101 +
b101101 !
b101101 &
1%
1'
#54
0%
0'
#57
b110010 ,
b110010 "
b110010 (
b110010 +
b110010 !
b110010 &
1%
1'
#60
0%
0'
#63
b110111 #
b110111 )
b110111 *
b110111 ,
b110111 "
b110111 (
b110111 +
b110111 !
b110111 &
1%
1'
#66
0%
0'
#69
b111100 ,
b111100 "
b111100 (
b111100 +
b111100 !
b111100 &
1%
1'
#72
0%
0'
#75
b1 #
b1 )
b1 *
b1000001 ,
b1000001 "
b1000001 (
b1 +
b1 !
b1 &
1%
1'
#78
0%
0'
#81
b1000110 ,
b1000110 "
b1000110 (
b110 +
b110 !
b110 &
1%
1'
#84
0%
0'
#87
b1011 #
b1011 )
b1011 *
b1001011 ,
b1001011 "
b1001011 (
b1011 +
b1011 !
b1011 &
1%
1'
#90
0%
0'
#93
b1010000 ,
b1010000 "
b1010000 (
b10000 +
b10000 !
b10000 &
1%
1'
#96
0%
0'
#99
b10101 #
b10101 )
b10101 *
b1010101 ,
b1010101 "
b1010101 (
b10101 +
b10101 !
b10101 &
1%
1'
#102
0%
0'
#105
b1011010 ,
b1011010 "
b1011010 (
b11010 +
b11010 !
b11010 &
1%
1'
#108
0%
0'
#111
b11111 #
b11111 )
b11111 *
b1011111 ,
b1011111 "
b1011111 (
b11111 +
b11111 !
b11111 &
1%
1'
#114
0%
0'
#117
b1100100 ,
b1100100 "
b1100100 (
b100100 +
b100100 !
b100100 &
1%
1'
#120
0%
0'
#123
b101001 #
b101001 )
b101001 *
b1101001 ,
b1101001 "
b1101001 (
b101001 +
b101001 !
b101001 &
1%
1'
#126
0%
0'
#129
b1101110 ,
b1101110 "
b1101110 (
b101110 +
b101110 !
b101110 &
1%
1'
#132
0%
0'
#135
b110011 #
b110011 )
b110011 *
b1110011 ,
b1110011 "
b1110011 (
b110011 +
b110011 !
b110011 &
1%
1'
#138
0%
0'
#141
b1111000 ,
b1111000 "
b1111000 (
b111000 +
b111000 !
b111000 &
1%
1'
#144
0%
0'
#147
b111101 #
b111101 )
b111101 *
b1111101 ,
b1111101 "
b1111101 (
b111101 +
b111101 !
b111101 &
1%
1'
#150
0%
0'
#153
b10000010 ,
b10000010 "
b10000010 (
b10 +
b10 !
b10 &
1%
1'
#156
0%
0'
#159
b111 #
b111 )
b111 *
b10000111 ,
b10000111 "
b10000111 (
b111 +
b111 !
b111 &
1%
1'
#162
0%
0'
#165
b10001100 ,
b10001100 "
b10001100 (
b1100 +
b1100 !
b1100 &
1%
1'
#168
0%
0'
#171
b10001 #
b10001 )
b10001 *
b10010001 ,
b10010001 "
b10010001 (
b10001 +
b10001 !
b10001 &
1%
1'
#174
0%
0'
#177
b10010110 ,
b10010110 "
b10010110 (
b10110 +
b10110 !
b10110 &
1%
1'
#180
0%
0'
#183
b11011 #
b11011 )
b11011 *
b10011011 ,
b10011011 "
b10011011 (
b11011 +
b11011 !
b11011 &
1%
1'
#186
0%
0'
#189
b10100000 ,
b10100000 "
b10100000 (
b100000 +
b100000 !
b100000 &
1%
1'
#192
0%
0'
#195
b100101 #
b100101 )
b100101 *
b10100101 ,
b10100101 "
b10100101 (
b100101 +
b100101 !
b100101 &
1%
1'
#198
0%
0'
#201
b10101010 ,
b10101010 "
b10101010 (
b101010 +
b101010 !
b101010 &
1%
1'
#204
0%
0'
#207
b101111 #
b101111 )
b101111 *
b10101111 ,
b10101111 "
b10101111 (
b101111 +
b101111 !
b101111 &
1%
1'
#210
0%
0'
#213
b10110100 ,
b10110100 "
b10110100 (
b110100 +
b110100 !
b110100 &
1%
1'
#216
0%
0'
#219
b111001 #
b111001 )
b111001 *
b10111001 ,
b10111001 "
b10111001 (
b111001 +
b111001 !
b111001 &
1%
1'
#222
0%
0'
#225
b10111110 ,
b10111110 "
b10111110 (
b111110 +
b111110 !
b111110 &
1%
1'
#228
0%
0'
#231
b11 #
b11 )
b11 *
b11000011 ,
b11000011 "
b11000011 (
b11 +
b11 !
b11 &
1%
1'
#234
0%
0'
#237
b11001000 ,
b11001000 "
b11001000 (
b1000 +
b1000 !
b1000 &
1%
1'
#240
0%
0'
#243
b1101 #
b1101 )
b1101 *
b11001101 ,
b11001101 "
b11001101 (
b1101 +
b1101 !
b1101 &
1%
1'
#246
0%
0'
#249
b11010010 ,
b11010010 "
b11010010 (
b10010 +
b10010 !
b10010 &
1%
1'
#252
0%
0'
#255
b10111 #
b10111 )
b10111 *
b11010111 ,
b11010111 "
b11010111 (
b10111 +
b10111 !
b10111 &
1%
1'
#258
0%
0'
#261
b11011100 ,
b11011100 "
b11011100 (
b11100 +
b11100 !
b11100 &
1%
1'
#264
0%
0'
#267
b100001 #
b100001 )
b100001 *
b11100001 ,
b11100001 "
b11100001 (
b100001 +
b100001 !
b100001 &
1%
1'
#270
0%
0'
#273
b11100110 ,
b11100110 "
b11100110 (
b100110 +
b100110 !
b100110 &
1%
1'
#276
0%
0'
#279
b101011 #
b101011 )
b101011 *
b11101011 ,
b11101011 "
b11101011 (
b101011 +
b101011 !
b101011 &
1%
1'
#282
0%
0'
#285
b11110000 ,
b11110000 "
b11110000 (
b110000 +
b110000 !
b110000 &
1%
1'
#288
0%
0'
#291
b110101 #
b110101 )
b110101 *
b11110101 ,
b11110101 "
b11110101 (
b110101 +
b110101 !
b110101 &
1%
1'
#294
0%
0'
#297
b11111010 ,
b11111010 "
b11111010 (
b111010 +
b111010 !
b111010 &
1%
1'
#300
0%
0'
#303
b111111 #
b111111 )
b111111 *
b11111111 ,
b11111111 "
b11111111 (
b111111 +
b111111 !
b111111 &
1%
1'
#306
0%
0'
#309
b100 ,
b100 "
b100 (
b100 +
b100 !
b100 &
1%
1'
#312
0%
0'
#315
b1001 #
b1001 )
b1001 *
b1001 ,
b1001 "
b1001 (
b1001 +
b1001 !
b1001 &
1%
1'
#318
0%
0'
#321
b1110 ,
b1110 "
b1110 (
b1110 +
b1110 !
b1110 &
1%
1'
#324
0%
0'
#327
b10011 #
b10011 )
b10011 *
b10011 ,
b10011 "
b10011 (
b10011 +
b10011 !
b10011 &
1%
1'
#330
0%
0'
#333
b11000 ,
b11000 "
b11000 (
b11000 +
b11000 !
b11000 &
1%
1'
#336
0%
0'
#339
b11101 #
b11101 )
b11101 *
b11101 ,
b11101 "
b11101 (
b11101 +
b11101 !
b11101 &
1%
1'
#342
0%
0'
#345
b100010 ,
b100010 "
b100010 (
b100010 +
b100010 !
b100010 &
1%
1'
#348
0%
0'
#351
b100111 #
b100111 )
b100111 *
b100111 ,
b100111 "
b100111 (
b100111 +
b100111 !
b100111 &
1%
1'
#354
0%
0'
#357
b101100 ,
b101100 "
b101100 (
b101100 +
b101100 !
b101100 &
1%
1'
#360
0%
0'
#363
b110001 #
b110001 )
b110001 *
b110001 ,
b110001 "
b110001 (
b110001 +
b110001 !
b110001 &
1%
1'
#366
0%
0'
#369
b110110 ,
b110110 "
b110110 (
b110110 +
b110110 !
b110110 &
1%
1'
#372
0%
0'
#375
b111011 #
b111011 )
b111011 *
b111011 ,
b111011 "
b111011 (
b111011 +
b111011 !
b111011 &
1%
1'
#378
0%
0'
#381
b1000000 ,
b1000000 "
b1000000 (
b0 +
b0 !
b0 &
1%
1'
#384
0%
0'
#387
b101 #
b101 )
b101 *
b1000101 ,
b1000101 "
b1000101 (
b101 +
b101 !
b101 &
1%
1'
#390
0%
0'
#393
b1001010 ,
b1001010 "
b1001010 (
b1010 +
b1010 !
b1010 &
1%
1'
#396
0%
0'
#399
b1111 #
b1111 )
b1111 *
b1001111 ,
b1001111 "
b1001111 (
b1111 +
b1111 !
b1111 &
1%
1'
#402
0%
0'
#405
b1010100 ,
b1010100 "
b1010100 (
b10100 +
b10100 !
b10100 &
1%
1'
#408
0%
0'
#411
b11001 #
b11001 )
b11001 *
b1011001 ,
b1011001 "
b1011001 (
b11001 +
b11001 !
b11001 &
1%
1'
#414
0%
0'
#417
b1011110 ,
b1011110 "
b1011110 (
b11110 +
b11110 !
b11110 &
1%
1'
#420
0%
0'
#423
b100011 #
b100011 )
b100011 *
b1100011 ,
b1100011 "
b1100011 (
b100011 +
b100011 !
b100011 &
1%
1'
#426
0%
0'
#429
b1101000 ,
b1101000 "
b1101000 (
b101000 +
b101000 !
b101000 &
1%
1'
#432
0%
0'
#435
b101101 #
b101101 )
b101101 *
b1101101 ,
b1101101 "
b1101101 (
b101101 +
b101101 !
b101101 &
1%
1'
#438
0%
0'
#441
b1110010 ,
b1110010 "
b1110010 (
b110010 +
b110010 !
b110010 &
1%
1'
#444
0%
0'
#447
b110111 #
b110111 )
b110111 *
b1110111 ,
b1110111 "
b1110111 (
b110111 +
b110111 !
b110111 &
1%
1'
#450
0%
0'
#453
b1111100 ,
b1111100 "
b1111100 (
b111100 +
b111100 !
b111100 &
1%
1'
#456
0%
0'
#459
b1 #
b1 )
b1 *
b10000001 ,
b10000001 "
b10000001 (
b1 +
b1 !
b1 &
1%
1'
#462
0%
0'
#465
b10000110 ,
b10000110 "
b10000110 (
b110 +
b110 !
b110 &
1%
1'
#468
0%
0'
#471
b1011 #
b1011 )
b1011 *
b10001011 ,
b10001011 "
b10001011 (
b1011 +
b1011 !
b1011 &
1%
1'
#474
0%
0'
#477
b10010000 ,
b10010000 "
b10010000 (
b10000 +
b10000 !
b10000 &
1%
1'
#480
0%
0'
#483
b10101 #
b10101 )
b10101 *
b10010101 ,
b10010101 "
b10010101 (
b10101 +
b10101 !
b10101 &
1%
1'
#486
0%
0'
#489
b10011010 ,
b10011010 "
b10011010 (
b11010 +
b11010 !
b11010 &
1%
1'
#492
0%
0'
#495
b11111 #
b11111 )
b11111 *
b10011111 ,
b10011111 "
b10011111 (
b11111 +
b11111 !
b11111 &
1%
1'
#498
0%
0'
#501
b10100100 ,
b10100100 "
b10100100 (
b100100 +
b100100 !
b100100 &
1%
1'
#504
0%
0'
#507
b101001 #
b101001 )
b101001 *
b10101001 ,
b10101001 "
b10101001 (
b101001 +
b101001 !
b101001 &
1%
1'
#510
0%
0'
#513
b10101110 ,
b10101110 "
b10101110 (
b101110 +
b101110 !
b101110 &
1%
1'
#516
0%
0'
#519
b110011 #
b110011 )
b110011 *
b10110011 ,
b10110011 "
b10110011 (
b110011 +
b110011 !
b110011 &
1%
1'
#522
0%
0'
#525
b10111000 ,
b10111000 "
b10111000 (
b111000 +
b111000 !
b111000 &
1%
1'
#528
0%
0'
#531
b111101 #
b111101 )
b111101 *
b10111101 ,
b10111101 "
b10111101 (
b111101 +
b111101 !
b111101 &
1%
1'
#534
0%
0'
#537
b11000010 ,
b11000010 "
b11000010 (
b10 +
b10 !
b10 &
1%
1'
#540
0%
0'
#543
b111 #
b111 )
b111 *
b11000111 ,
b11000111 "
b11000111 (
b111 +
b111 !
b111 &
1%
1'
#546
0%
0'
#549
b11001100 ,
b11001100 "
b11001100 (
b1100 +
b1100 !
b1100 &
1%
1'
#552
0%
0'
#555
b10001 #
b10001 )
b10001 *
b11010001 ,
b11010001 "
b11010001 (
b10001 +
b10001 !
b10001 &
1%
1'
#558
0%
0'
#561
b11010110 ,
b11010110 "
b11010110 (
b10110 +
b10110 !
b10110 &
1%
1'
#564
0%
0'
#567
b11011 #
b11011 )
b11011 *
b11011011 ,
b11011011 "
b11011011 (
b11011 +
b11011 !
b11011 &
1%
1'
#570
0%
0'
#573
b11100000 ,
b11100000 "
b11100000 (
b100000 +
b100000 !
b100000 &
1%
1'
#576
0%
0'
#579
b100101 #
b100101 )
b100101 *
b11100101 ,
b11100101 "
b11100101 (
b100101 +
b100101 !
b100101 &
1%
1'
#582
0%
0'
#585
b11101010 ,
b11101010 "
b11101010 (
b101010 +
b101010 !
b101010 &
1%
1'
#588
0%
0'
#591
b101111 #
b101111 )
b101111 *
b11101111 ,
b11101111 "
b11101111 (
b101111 +
b101111 !
b101111 &
1%
1'
#594
0%
0'
#597
b11110100 ,
b11110100 "
b11110100 (
b110100 +
b110100 !
b110100 &
1%
1'
#600
0%
0'
#603
b111001 #
b111001 )
b111001 *
b11111001 ,
b11111001 "
b11111001 (
b111001 +
b111001 !
b111001 &
1%
1'
#606
0%
0'
#609
b11111110 ,
b11111110 "
b11111110 (
b111110 +
b111110 !
b111110 &
1%
1'
#612
0%
0'
#615
b11 #
b11 )
b11 *
b11 ,
b11 "
b11 (
b11 +
b11 !
b11 &
1%
1'
#618
0%
0'
#621
b1000 ,
b1000 "
b1000 (
b1000 +
b1000 !
b1000 &
1%
1'
#624
0%
0'
#627
b1101 #
b1101 )
b1101 *
b1101 ,
b1101 "
b1101 (
b1101 +
b1101 !
b1101 &
1%
1'
#630
0%
0'
#633
b10010 ,
b10010 "
b10010 (
b10010 +
b10010 !
b10010 &
1%
1'
#636
0%
0'
#639
b10111 #
b10111 )
b10111 *
b10111 ,
b10111 "
b10111 (
b10111 +
b10111 !
b10111 &
1%
1'
#642
0%
0'
#645
b11100 ,
b11100 "
b11100 (
b11100 +
b11100 !
b11100 &
1%
1'
#648
0%
0'
#651
b100001 #
b100001 )
b100001 *
b100001 ,
b100001 "
b100001 (
b100001 +
b100001 !
b100001 &
1%
1'
#654
0%
0'
#657
b100110 ,
b100110 "
b100110 (
b100110 +
b100110 !
b100110 &
1%
1'
#660
0%
0'
#663
b101011 #
b101011 )
b101011 *
b101011 ,
b101011 "
b101011 (
b101011 +
b101011 !
b101011 &
1%
1'
#666
0%
0'
#669
b110000 ,
b110000 "
b110000 (
b110000 +
b110000 !
b110000 &
1%
1'
#672
0%
0'
#675
b110101 #
b110101 )
b110101 *
b110101 ,
b110101 "
b110101 (
b110101 +
b110101 !
b110101 &
1%
1'
#678
0%
0'
#681
b111010 ,
b111010 "
b111010 (
b111010 +
b111010 !
b111010 &
1%
1'
#684
0%
0'
#687
b111111 #
b111111 )
b111111 *
b111111 ,
b111111 "
b111111 (
b111111 +
b111111 !
b111111 &
1%
1'
#690
0%
0'
#693
b1000100 ,
b1000100 "
b1000100 (
b100 +
b100 !
b100 &
1%
1'
#696
0%
0'
#699
b1001 #
b1001 )
b1001 *
b1001001 ,
b1001001 "
b1001001 (
b1001 +
b1001 !
b1001 &
1%
1'
#702
0%
0'
#705
b1001110 ,
b1001110 "
b1001110 (
b1110 +
b1110 !
b1110 &
1%
1'
#708
0%
0'
#711
b10011 #
b10011 )
b10011 *
b1010011 ,
b1010011 "
b1010011 (
b10011 +
b10011 !
b10011 &
1%
1'
#714
0%
0'
#717
b1011000 ,
b1011000 "
b1011000 (
b11000 +
b11000 !
b11000 &
1%
1'
#720
0%
0'
#723
b11101 #
b11101 )
b11101 *
b1011101 ,
b1011101 "
b1011101 (
b11101 +
b11101 !
b11101 &
1%
1'
#726
0%
0'
#729
b1100010 ,
b1100010 "
b1100010 (
b100010 +
b100010 !
b100010 &
1%
1'
#732
0%
0'
#735
b100111 #
b100111 )
b100111 *
b1100111 ,
b1100111 "
b1100111 (
b100111 +
b100111 !
b100111 &
1%
1'
#738
0%
0'
#741
b1101100 ,
b1101100 "
b1101100 (
b101100 +
b101100 !
b101100 &
1%
1'
#744
0%
0'
#747
b110001 #
b110001 )
b110001 *
b1110001 ,
b1110001 "
b1110001 (
b110001 +
b110001 !
b110001 &
1%
1'
#750
0%
0'
#753
b1110110 ,
b1110110 "
b1110110 (
b110110 +
b110110 !
b110110 &
1%
1'
#756
0%
0'
#759
b111011 #
b111011 )
b111011 *
b1111011 ,
b1111011 "
b1111011 (
b111011 +
b111011 !
b111011 &
1%
1'
#762
0%
0'
#765
b10000000 ,
b10000000 "
b10000000 (
b0 +
b0 !
b0 &
1%
1'
#768
0%
0'
#771
b101 #
b101 )
b101 *
b10000101 ,
b10000101 "
b10000101 (
b101 +
b101 !
b101 &
1%
1'
#774
0%
0'
#777
b10001010 ,
b10001010 "
b10001010 (
b1010 +
b1010 !
b1010 &
1%
1'
#780
0%
0'
#783
b1111 #
b1111 )
b1111 *
b10001111 ,
b10001111 "
b10001111 (
b1111 +
b1111 !
b1111 &
1%
1'
#786
0%
0'
#789
b10010100 ,
b10010100 "
b10010100 (
b10100 +
b10100 !
b10100 &
1%
1'
#792
0%
0'
#795
b11001 #
b11001 )
b11001 *
b10011001 ,
b10011001 "
b10011001 (
b11001 +
b11001 !
b11001 &
1%
1'
#798
0%
0'
#801
b10011110 ,
b10011110 "
b10011110 (
b11110 +
b11110 !
b11110 &
1%
1'
#804
0%
0'
#807
b100011 #
b100011 )
b100011 *
b10100011 ,
b10100011 "
b10100011 (
b100011 +
b100011 !
b100011 &
1%
1'
#810
0%
0'
#813
b10101000 ,
b10101000 "
b10101000 (
b101000 +
b101000 !
b101000 &
1%
1'
#816
0%
0'
#819
b101101 #
b101101 )
b101101 *
b10101101 ,
b10101101 "
b10101101 (
b101101 +
b101101 !
b101101 &
1%
1'
#822
0%
0'
#825
b10110010 ,
b10110010 "
b10110010 (
b110010 +
b110010 !
b110010 &
1%
1'
#828
0%
0'
#831
b110111 #
b110111 )
b110111 *
b10110111 ,
b10110111 "
b10110111 (
b110111 +
b110111 !
b110111 &
1%
1'
#834
0%
0'
#837
b10111100 ,
b10111100 "
b10111100 (
b111100 +
b111100 !
b111100 &
1%
1'
#840
0%
0'
#843
b1 #
b1 )
b1 *
b11000001 ,
b11000001 "
b11000001 (
b1 +
b1 !
b1 &
1%
1'
#846
0%
0'
#849
b11000110 ,
b11000110 "
b11000110 (
b110 +
b110 !
b110 &
1%
1'
#852
0%
0'
#855
b1011 #
b1011 )
b1011 *
b11001011 ,
b11001011 "
b11001011 (
b1011 +
b1011 !
b1011 &
1%
1'
#858
0%
0'
#861
b11010000 ,
b11010000 "
b11010000 (
b10000 +
b10000 !
b10000 &
1%
1'
#864
0%
0'
#867
b10101 #
b10101 )
b10101 *
b11010101 ,
b11010101 "
b11010101 (
b10101 +
b10101 !
b10101 &
1%
1'
#870
0%
0'
#873
b11011010 ,
b11011010 "
b11011010 (
b11010 +
b11010 !
b11010 &
1%
1'
#876
0%
0'
#879
b11111 #
b11111 )
b11111 *
b11011111 ,
b11011111 "
b11011111 (
b11111 +
b11111 !
b11111 &
1%
1'
#882
0%
0'
#885
b11100100 ,
b11100100 "
b11100100 (
b100100 +
b100100 !
b100100 &
1%
1'
#888
0%
0'
#891
b101001 #
b101001 )
b101001 *
b11101001 ,
b11101001 "
b11101001 (
b101001 +
b101001 !
b101001 &
1%
1'
#894
0%
0'
#897
b11101110 ,
b11101110 "
b11101110 (
b101110 +
b101110 !
b101110 &
1%
1'
#900
0%
0'
#903
b110011 #
b110011 )
b110011 *
b11110011 ,
b11110011 "
b11110011 (
b110011 +
b110011 !
b110011 &
1%
1'
#906
0%
0'
#909
b11111000 ,
b11111000 "
b11111000 (
b111000 +
b111000 !
b111000 &
1%
1'
#912
0%
0'
#915
b111101 #
b111101 )
b111101 *
b11111101 ,
b11111101 "
b11111101 (
b111101 +
b111101 !
b111101 &
1%
1'
#918
0%
0'
#921
b10 ,
b10 "
b10 (
b10 +
b10 !
b10 &
1%
1'
#924
0%
0'
#927
b111 #
b111 )
b111 *
b111 ,
b111 "
b111 (
b111 +
b111 !
b111 &
1%
1'
#930
0%
0'
#933
b1100 ,
b1100 "
b1100 (
b1100 +
b1100 !
b1100 &
1%
1'
#936
0%
0'
#939
b10001 #
b10001 )
b10001 *
b10001 ,
b10001 "
b10001 (
b10001 +
b10001 !
b10001 &
1%
1'
#942
0%
0'
#945
b10110 ,
b10110 "
b10110 (
b10110 +
b10110 !
b10110 &
1%
1'
#948
0%
0'
#951
b11011 #
b11011 )
b11011 *
b11011 ,
b11011 "
b11011 (
b11011 +
b11011 !
b11011 &
1%
1'
#954
0%
0'
#957
b100000 ,
b100000 "
b100000 (
b100000 +
b100000 !
b100000 &
1%
1'
#960
0%
0'
#963
b100101 #
b100101 )
b100101 *
b100101 ,
b100101 "
b100101 (
b100101 +
b100101 !
b100101 &
1%
1'
#966
0%
0'
#969
b101010 ,
b101010 "
b101010 (
b101010 +
b101010 !
b101010 &
1%
1'
#972
0%
0'
#975
b101111 #
b101111 )
b101111 *
b101111 ,
b101111 "
b101111 (
b101111 +
b101111 !
b101111 &
1%
1'
#978
0%
0'
#981
b110100 ,
b110100 "
b110100 (
b110100 +
b110100 !
b110100 &
1%
1'
#984
0%
0'
#987
b111001 #
b111001 )
b111001 *
b111001 ,
b111001 "
b111001 (
b111001 +
b111001 !
b111001 &
1%
1'
#990
0%
0'
#993
b111110 ,
b111110 "
b111110 (
b111110 +
b111110 !
b111110 &
1%
1'
#996
0%
0'
#999
b11 #
b11 )
b11 *
b1000011 ,
b1000011 "
b1000011 (
b11 +
b11 !
b11 &
1%
1'
