Machine/machine_teacher/maquina.v
module maquina
   (output reg valvula_agua, modo_agitar, modo_girar,
    input clock, reset_n, inicio, tempo, cheio, secar);
    
    reg [1:0] estado_atual;
    parameter espera = 0, encher =1, agitar = 2, girar = 3;
    
    always @ (*) begin   // parte combinacional
      case (estado_atual)
       espera: begin
                valvula_agua =0; modo_agitar=0; modo_girar=0;
               end               
       encher: begin
                valvula_agua=1; modo_agitar=0; modo_girar=0;
               end                         
       agitar: begin
                valvula_agua=0; modo_agitar=1; modo_girar=0;  
               end
       girar:  begin
                valvula_agua =0; modo_agitar=0; modo_girar=1;
               end           
      endcase    
    end 
	always @ (posedge clock, negedge reset_n) // parte sequencial
     if (~reset_n)
      estado_atual <= espera;
     else 
      case (estado_atual)
       espera: if (inicio == 1)
                estado_atual <= encher;
                
       encher: if (cheio == 1) 
                estado_atual <= agitar; 
      
       agitar: if (tempo == 1)            
                 estado_atual <= girar;   
               
        girar: if (secar == 0)       
                 estado_atual <= espera;   
		default: estado_atual<=espera;
       endcase
      endmodule

Machine/machine_teacher/maquina_tb.v
`include "maquina.v"
module maquina_tb;
reg inicio, cheio, tempo, secar, reset_n, clock;
maquina maquina(.inicio (inicio), .cheio (cheio), .tempo (tempo), .secar(secar), .reset_n(reset_n), .clock(clock));
initial begin
	$dumpfile("maquina.vcd");  //especifica em qual arquivo serao armazenadas as formas de onda
	$dumpvars;  //especifica para colocar todos os sinais no counter.vcd 
	
	inicio = 0;
	cheio = 0;
	tempo =1;
	secar=1;
	clock = 0;
	#10;
	reset_n=0;
	#10;
	reset_n=1;
	#10;
	inicio = 1;
	cheio= 1;
	tempo=1;
	secar=1;
	#10;
	inicio = 1;
	cheio= 1;
	tempo=1;
	secar=0;
#10;
	inicio = 1;
	cheio= 1;
	tempo=1;
	secar=0;	
	
	
	#10;
	inicio = 1;
	cheio= 1;
	tempo=1;
	secar=0;	
	#10;
	inicio = 1;
	cheio= 1;
	tempo=1;
	secar=0;	
	
	
	#150 $finish;
 end

always
	#5 clock = ~clock;
 
endmodule

Machine/machine_teacher/maquina.vcd
$date
	Tue Apr 17 16:41:32 2018
$end
$version
	Icarus Verilog
$end
$timescale
	1s
$end
$scope module maquina_tb $end
$var reg 1 ! cheio $end
$var reg 1 " clock $end
$var reg 1 # inicio $end
$var reg 1 $ reset_n $end
$var reg 1 % secar $end
$var reg 1 & tempo $end
$scope module maquina $end
$var wire 1 ! cheio $end
$var wire 1 " clock $end
$var wire 1 # inicio $end
$var wire 1 $ reset_n $end
$var wire 1 % secar $end
$var wire 1 & tempo $end
$var reg 2 ' estado_atual [1:0] $end
$var reg 1 ( modo_agitar $end
$var reg 1 ) modo_girar $end
$var reg 1 * valvula_agua $end
$upscope $end
$upscope $end
$enddefinitions $end
#0
$dumpvars
x*
x)
x(
bx '
1&
1%
x$
0#
0"
0!
$end
#5
0)
0(
0*
b0 '
1"
#10
0"
0$
#15
1"
#20
0"
1$
#25
1"
#30
0"
1!
1#
#35
1*
b1 '
1"
#40
0"
0%
#45
1(
0*
b10 '
1"
#50
0"
#55
1)
0(
b11 '
1"
#60
0"
#65
0)
b0 '
1"
#70
0"
#75
1*
b1 '
1"
#80
0"
#85
1(
0*
b10 '
1"
#90
0"
#95
1)
0(
b11 '
1"
#100
0"
#105
0)
b0 '
1"
#110
0"
#115
1*
b1 '
1"
#120
0"
#125
1(
0*
b10 '
1"
#130
0"
#135
1)
0(
b11 '
1"
#140
0"
#145
0)
b0 '
1"
#150
0"
#155
1*
b1 '
1"
#160
0"
#165
1(
0*
b10 '
1"
#170
0"
#175
1)
0(
b11 '
1"
#180
0"
#185
0)
b0 '
1"
#190
0"
#195
1*
b1 '
1"
#200
0"
#205
1(
0*
b10 '
1"
#210
0"
#215
1)
0(
b11 '
1"
